pygen/exceptions.py
pygen/index.py
pygen/scope.py
pygen/scripts.py
pygen/target.py
pygen/target_template.py
pygen/__init__.py
pygen/parsers/base.py
pygen/parsers/json.py
pygen/parsers/yaml.py
pygen/parsers/__init__.py
pygen-0.0.2.dist-info/DESCRIPTION.rst
pygen-0.0.2.dist-info/entry_points.txt
pygen-0.0.2.dist-info/METADATA
pygen-0.0.2.dist-info/metadata.json
pygen-0.0.2.dist-info/RECORD
pygen-0.0.2.dist-info/top_level.txt
pygen-0.0.2.dist-info/WHEEL
