Metadata-Version: 2.0
Name: pygen
Version: 0.0.2
Summary: A versatile and extensible file generation tool.
Home-page: http://ereOn.github.io/pygen
Author: Julien Kauffmann
Author-email: julien.kauffmann@freelan.org
License: UNKNOWN
Platform: UNKNOWN
Classifier: Intended Audience :: Developers
Classifier: Operating System :: OS Independent
Classifier: Programming Language :: Python :: 2
Classifier: Programming Language :: Python :: 2.7
Classifier: Programming Language :: Python :: 3
Classifier: Programming Language :: Python :: 3.3
Classifier: Programming Language :: Python :: 3.4
Classifier: Programming Language :: Python :: 3.5
Classifier: Topic :: Software Development
Classifier: Topic :: Software Development :: Libraries :: Python Modules
Classifier: Development Status :: 5 - Production/Stable
Requires-Dist: six (==1.10.0)
Requires-Dist: future (==0.15.2)
Requires-Dist: Jinja2 (==2.8)
Requires-Dist: click (==6.2)
Requires-Dist: PyYAML (==3.11)
Requires-Dist: voluptuous (==0.8.8)
Requires-Dist: colorama (==0.3.6)
Requires-Dist: requests (==2.9.1)
